isbtchot/__init__.py
isbtchot/__main__.py
isbtchot/controller.py
isbtchot/model.py
isbtchot/view.py
isbtchot/schemas/args.py
isbtchot-1.1.5.dist-info/licenses/LICENSE
isbtchot-1.1.5.dist-info/METADATA
isbtchot-1.1.5.dist-info/WHEEL
isbtchot-1.1.5.dist-info/top_level.txt
isbtchot-1.1.5.dist-info/RECORD
