Metadata-Version: 2.4
Name: isbtchot
Version: 1.1.5
Summary: TBD
Author-email: Daniel <dakixr@gmail.com>
License-File: LICENSE
Requires-Dist: pandas
Requires-Dist: plotext
Requires-Dist: requests
Requires-Dist: scikit-learn
Dynamic: license-file
